README.md
setup.py
x64trace/__init__.py
x64trace/__main__.py
x64trace/registers.py
x64trace/trace.py
x64trace.egg-info/PKG-INFO
x64trace.egg-info/SOURCES.txt
x64trace.egg-info/dependency_links.txt
x64trace.egg-info/entry_points.txt
x64trace.egg-info/requires.txt
x64trace.egg-info/top_level.txt