Metadata-Version: 2.1
Name: x64trace
Version: 1.0.0
Summary: Library for loading x64dbg Trace Files
Home-page: https://github.com/thestr4ng3r/x64trace-py
Author: Florian Märkl
License: LGPLv3
Keywords: x64dbg trace
Platform: UNKNOWN
Requires-Python: >=3.7
Provides-Extra: disassembly
